OptiPose/__init__.py
cvkit_optipose/__init__.py
cvkit_optipose-0.0.1.dist-info/METADATA
cvkit_optipose-0.0.1.dist-info/WHEEL
cvkit_optipose-0.0.1.dist-info/top_level.txt
cvkit_optipose-0.0.1.dist-info/RECORD
