Metadata-Version: 2.1
Name: cvkit-optipose
Version: 0.0.1
Summary: Postural auto-encoder
Author-email: Mahir Patel <mahirp@bu.edu>
Project-URL: repository, https://github.com/mahir1010/OptiPose
Classifier: Topic :: Scientific/Engineering :: Artificial Intelligence
Classifier: Programming Language :: Python :: 3
Classifier: License :: OSI Approved :: MIT License
Classifier: Operating System :: OS Independent
Requires-Python: >=3.10
Requires-Dist: bu-cvkit
Requires-Dist: matplotlib (==3.7.1)
Requires-Dist: numpy (==1.24.2)
Requires-Dist: scipy (==1.10.1)
Requires-Dist: tensorflow (==2.11.0)
